buildpub/__init__.py
buildpub/main.py
buildpub-0.1.1.dist-info/licenses/LICENSE
buildpub-0.1.1.dist-info/METADATA
buildpub-0.1.1.dist-info/WHEEL
buildpub-0.1.1.dist-info/entry_points.txt
buildpub-0.1.1.dist-info/top_level.txt
buildpub-0.1.1.dist-info/RECORD
