Metadata-Version: 2.4
Name: buildpub
Version: 0.1.1
Summary: A simple Docker image builder and publisher
Author: Tulio Amancio
License: MIT
Classifier: Programming Language :: Python :: 3
Classifier: License :: OSI Approved :: MIT License
Classifier: Operating System :: OS Independent
Classifier: Topic :: Software Development :: Build Tools
Classifier: Topic :: System :: Software Distribution
Requires-Python: >=3.9
License-File: LICENSE
Requires-Dist: GitPython>=3.1.41
Requires-Dist: docker>=6.1.3
Requires-Dist: loguru>=0.7.2
Requires-Dist: urllib3<2.0.0
Requires-Dist: requests==2.31.0
Provides-Extra: dev
Requires-Dist: build; extra == "dev"
Requires-Dist: twine; extra == "dev"
Requires-Dist: pytest; extra == "dev"
Requires-Dist: black; extra == "dev"
Requires-Dist: isort; extra == "dev"
Requires-Dist: flake8; extra == "dev"
Requires-Dist: mypy; extra == "dev"
Dynamic: license-file
